kara_kanji_sync/__init__.py
kara_kanji_sync/kanji_syncer.py
kara_kanji_sync/lyrics.py
kara_kanji_sync/pronunciation.py
kara_kanji_sync/tests.py
kara_kanji_sync/utils.py
kara_kanji_sync/resources/JmdictFurigana.json
kara_kanji_sync/resources/manual_additions.json
kara_kanji_sync/resources/template.ass
kara_kanji_sync-0.1.12.dist-info/METADATA
kara_kanji_sync-0.1.12.dist-info/WHEEL
kara_kanji_sync-0.1.12.dist-info/licenses/LICENSE
kara_kanji_sync-0.1.12.dist-info/RECORD
