Metadata-Version: 2.4
Name: kara_kanji_sync
Version: 0.1.12
Summary: Align kanji lyrics with romaji karaokes
License-Expression: MIT
License-File: LICENSE
Requires-Python: >=3.12
Requires-Dist: jisho-api>=0.1.8
Requires-Dist: mecab-python3>=1.0.10
Requires-Dist: pykakasi>=2.3.0
Requires-Dist: pysubs2>=1.8.0
Requires-Dist: unidic-lite>=1.0.8
Requires-Dist: wanakana-python>=1.2.2
